<scene_elements>
  <node>
    <class>javafx.scene.text.Text</class>
    <type>TEXT</type>
    <text>ROUND</text>
    <x_layout_factor>0.89</x_layout_factor>
    <y_layout_factor>0.12</y_layout_factor>
    <style>game-text</style>
    <event_type>MANAGE_GAME_STATS</event_type>
    <event>SET_ROUND</event>
  </node>

  <node>
    <class>javafx.scene.text.Text</class>
    <type>TEXT</type>
    <text>TURN</text>
    <x_layout_factor>0.87</x_layout_factor>
    <y_layout_factor>0.17</y_layout_factor>
    <style>game-text</style>
    <event_type>MANAGE_GAME_STATS</event_type>
    <event>SET_TURN</event>
  </node>

  <node>
    <class>javafx.scene.control.ListView</class>
    <type>LISTVIEW</type>
    <width_factor>0.12</width_factor>
    <height_factor>0.15</height_factor>
    <x_layout_factor>0.86</x_layout_factor>
    <y_layout_factor>0.2</y_layout_factor>
    <style>score-list</style>
    <event_type>MANAGE_GAME_STATS</event_type>
    <event>SET_SCORE</event>
  </node>

  <node>
    <class>javafx.scene.control.Button</class>
    <type>BUTTON</type>
    <text>PAUSE</text>
    <width_factor>0.05</width_factor>
    <height_factor>0.05</height_factor>
    <x_layout_factor>0.92</x_layout_factor>
    <y_layout_factor>0.4</y_layout_factor>
    <style>game-button</style>
    <event_type>MANAGE_GAME_PLAY</event_type>
    <event>PAUSE</event>
  </node>

  <node>
    <class>javafx.scene.control.Button</class>
    <type>BUTTON</type>
    <text>SAVE</text>
    <width_factor>0.05</width_factor>
    <height_factor>0.05</height_factor>
    <x_layout_factor>0.92</x_layout_factor>
    <y_layout_factor>0.5</y_layout_factor>
    <style>game-button</style>
    <event_type>MANAGE_GAME_PLAY</event_type>
    <event>SAVE</event>
  </node>

  <node>
    <class>javafx.scene.control.Button</class>
    <type>BUTTON</type>
    <text>BACK</text>
    <width_factor>0.05</width_factor>
    <height_factor>0.05</height_factor>
    <x_layout_factor>0.92</x_layout_factor>
    <y_layout_factor>0.6</y_layout_factor>
    <style>game-button</style>
    <event_type>CHANGE_SCENE</event_type>
    <event>START_MENU</event>
  </node>

  <node>
    <class>javafx.scene.control.Button</class>
    <type>BUTTON</type>
    <text>ADD_GAME</text>
    <width_factor>0.07</width_factor>
    <height_factor>0.05</height_factor>
    <x_layout_factor>0.9</x_layout_factor>
    <y_layout_factor>0.7</y_layout_factor>
    <style>game-button</style>
    <event_type>CHANGE_SCENE</event_type>
    <event>NEW_GAME_WINDOW</event>
  </node>

  <node>
    <class>javafx.scene.shape.Rectangle</class>
    <type>RECTANGLE</type>
    <width_factor>0.07</width_factor>
    <height_factor>0.7</height_factor>
    <x_layout_factor>0.75</x_layout_factor>
    <y_layout_factor>0.05</y_layout_factor>
    <style>power-outline</style>
    <event_type>STRIKE</event_type>
    <event>POWER_HEIGHT</event>
  </node>

  <node>
    <class>javafx.scene.shape.Rectangle</class>
    <type>RECTANGLE</type>
    <width_factor>0.05</width_factor>
    <height_factor>0.01</height_factor>
    <x_layout_factor>0.76</x_layout_factor>
    <y_layout_factor>0.735</y_layout_factor>
    <style>power-bar</style>
    <event_type>STRIKE</event_type>
    <event>STRIKE</event>
    <event>SET_POWER</event>
  </node>

  <node>
    <class>oogasalad.view.visual_elements.Arrow</class>
    <type>ARROW</type>
    <x_layout_factor>0.79</x_layout_factor>
    <y_layout_factor>0.9</y_layout_factor>
    <stem_width>5</stem_width>
    <stem_height>60</stem_height>
    <arrow_width_offset>5</arrow_width_offset>
    <arrow_height_offset>8</arrow_height_offset>
    <style>angle-arrow</style>
    <event_type>STRIKE</event_type>
    <event>SET_ANGLE</event>
  </node>
</scene_elements>