<game_elements>
  <node>
    <type>TEXT</type>
    <text>Score</text>
    <x_layout_factor>0.93</x_layout_factor>
    <y_layout_factor>0.45</y_layout_factor>
    <styling>game-text</styling>
  </node>

  <node>
    <type>TEXT</type>
    <text>Turn</text>
    <x_layout_factor>0.93</x_layout_factor>
    <y_layout_factor>0.5</y_layout_factor>
    <styling>game-text</styling>
  </node>

  <node>
    <type>TEXT</type>
    <text>Round</text>
    <x_layout_factor>0.93</x_layout_factor>
    <y_layout_factor>0.55</y_layout_factor>
    <styling>game-text</styling>
  </node>
</game_elements>