<scene_elements>
  <node>
    <type>BUTTON</type>
    <text>Pause</text>
    <width_factor>0.05</width_factor>
    <height_factor>0.05</height_factor>
    <x_layout_factor>0.92</x_layout_factor>
    <y_layout_factor>0.4</y_layout_factor>
    <styling>game-button</styling>
    <event>PAUSE</event>
  </node>

  <node>
    <type>BUTTON</type>
    <text>Save</text>
    <width_factor>0.05</width_factor>
    <height_factor>0.05</height_factor>
    <x_layout_factor>0.92</x_layout_factor>
    <y_layout_factor>0.5</y_layout_factor>
    <styling>game-button</styling>
    <event>SAVE</event>
  </node>

  <node>
    <type>BUTTON</type>
    <text>Load</text>
    <width_factor>0.05</width_factor>
    <height_factor>0.05</height_factor>
    <x_layout_factor>0.92</x_layout_factor>
    <y_layout_factor>0.6</y_layout_factor>
    <styling>game-button</styling>
    <event>LOAD</event>
  </node>

  <node>
    <type>BUTTON</type>
    <text>Zoom In</text>
    <width_factor>0.07</width_factor>
    <height_factor>0.05</height_factor>
    <x_layout_factor>0.9</x_layout_factor>
    <y_layout_factor>0.7</y_layout_factor>
    <styling>game-button</styling>
    <event>ZOOM_IN</event>
  </node>

  <node>
    <type>BUTTON</type>
    <text>Reset Zoom</text>
    <width_factor>0.07</width_factor>
    <height_factor>0.05</height_factor>
    <x_layout_factor>0.9</x_layout_factor>
    <y_layout_factor>0.8</y_layout_factor>
    <styling>game-button</styling>
    <event>RESET_ZOOM</event>
  </node>

  <node>
    <type>BUTTON</type>
    <text>Zoom Out</text>
    <width_factor>0.07</width_factor>
    <height_factor>0.05</height_factor>
    <x_layout_factor>0.9</x_layout_factor>
    <y_layout_factor>0.9</y_layout_factor>
    <styling>game-button</styling>
    <event>ZOOM_OUT</event>
  </node>

</scene_elements>